typegenie/__cli__.py
typegenie/__init__.py
typegenie/api.py
typegenie/autocomplete.py
typegenie/lib.py
typegenie-0.3.0.dist-info/LICENSE
typegenie-0.3.0.dist-info/METADATA
typegenie-0.3.0.dist-info/WHEEL
typegenie-0.3.0.dist-info/entry_points.txt
typegenie-0.3.0.dist-info/top_level.txt
typegenie-0.3.0.dist-info/RECORD
